terminator/exceptions.py
terminator/terminators.py
terminator/decorators.py
terminator/__init__.py
terminator/tests.py
terminator/models.py
django_terminator-0.1.1.dist-info/top_level.txt
django_terminator-0.1.1.dist-info/DESCRIPTION.rst
django_terminator-0.1.1.dist-info/WHEEL
django_terminator-0.1.1.dist-info/RECORD
django_terminator-0.1.1.dist-info/METADATA
django_terminator-0.1.1.dist-info/pydist.json
