Metadata-Version: 2.0
Name: django-terminator
Version: 0.1.1
Summary: One time method executor for Django models
Home-page: http://github.com/KrzysiekJ/django-terminator
Author: Krzysztof Jurewicz
Author-email: krzysztof.jurewicz@gmail.com
License: UNKNOWN
Platform: UNKNOWN
Classifier: Development Status :: 3 - Alpha
Classifier: Environment :: Web Environment
Classifier: Framework :: Django
Classifier: Intended Audience :: Developers
Classifier: License :: OSI Approved :: MIT License
Classifier: Operating System :: OS Independent
Classifier: Programming Language :: Python
Classifier: Programming Language :: Python :: 2
Classifier: Programming Language :: Python :: 2.7
